geothermsim/__init__.py
geothermsim/basis.py
geothermsim/fluid.py
geothermsim/path.py
geothermsim/borefield/__init__.py
geothermsim/borefield/borefield.py
geothermsim/borefield/network.py
geothermsim/borehole/__init__.py
geothermsim/borehole/_tube.py
geothermsim/borehole/borehole.py
geothermsim/borehole/multiple_u_tube.py
geothermsim/borehole/single_u_tube.py
geothermsim/ground_heat_exchanger/__init__.py
geothermsim/ground_heat_exchanger/_ground_heat_exchanger.py
geothermsim/ground_heat_exchanger/coaxial_heat_exchanger.py
geothermsim/ground_heat_exchanger/u_tube_heat_exchanger.py
geothermsim/heat_transfer/__init__.py
geothermsim/heat_transfer/point_heat_source.py
geothermsim/plot/__init__.py
geothermsim/plot/_format_axis.py
geothermsim/plot/plot_basis.py
geothermsim/plot/plot_borefield.py
geothermsim/plot/plot_borehole.py
geothermsim/plot/plot_gfunction.py
geothermsim/plot/plot_ground_heat_exchanger.py
geothermsim/plot/plot_path.py
geothermsim/simulation/__init__.py
geothermsim/simulation/_temporal_superposition.py
geothermsim/simulation/gfunction.py
geothermsim/simulation/load_aggregation.py
geothermsim/simulation/load_history_reconstruction.py
geothermsim/simulation/simulation.py
geothermsim/thermal_resistance/__init__.py
geothermsim/thermal_resistance/conduction_thermal_resistance.py
geothermsim/thermal_resistance/convective_heat_transfer_coefficient.py
geothermsim/thermal_resistance/darcy_friction_factor.py
geothermsim/thermal_resistance/multipole.py
geothermsim/thermal_resistance/reynolds_number.py
geothermsim/utilities/__init__.py
geothermsim/utilities/comb.py
geothermsim/utilities/quad.py
geothermsim-0.3.0.dist-info/licenses/LICENSE.md
geothermsim-0.3.0.dist-info/METADATA
geothermsim-0.3.0.dist-info/WHEEL
geothermsim-0.3.0.dist-info/top_level.txt
geothermsim-0.3.0.dist-info/RECORD
