Metadata-Version: 2.4
Name: geothermsim
Version: 0.3.0
Summary: Scalable semi-analytical heat transfer simulation of geothermal borehole fields
Home-page: https://github.com/MassimoCimmino/geothermsim
Author: Massimo Cimmino
Author-email: massimo.cimmino@polymtl.ca
License: BSD-3-Clause
Keywords: Geothermal,Ground-source,Ground heat exchangers
Classifier: Development Status :: 3 - Alpha
Classifier: Intended Audience :: Science/Research
Classifier: License :: OSI Approved :: BSD License
Classifier: Natural Language :: English
Classifier: Operating System :: OS Independent
Classifier: Programming Language :: Python :: 3
Classifier: Programming Language :: Python :: 3 :: Only
Classifier: Programming Language :: Python :: 3.10
Classifier: Programming Language :: Python :: 3.11
Classifier: Programming Language :: Python :: 3.12
Classifier: Programming Language :: Python :: 3.13
Classifier: Topic :: Scientific/Engineering
License-File: LICENSE.md
Requires-Dist: interpax>=0.3.8
Requires-Dist: jax>=0.6.0
Requires-Dist: matplotlib>=3.10.0
Requires-Dist: numpy>=2.2.2
Requires-Dist: pandas>=2.2.3
Requires-Dist: SecondaryCoolantProps>=1.3.0
Requires-Dist: scipy>=1.15.1
Requires-Dist: typing_extensions>=4.14.0
Dynamic: license-file
